spyc_iot/__init__.py
spyc_iot/bme280.py
spyc_iot/max7219.py
spyc_iot/ntp.py
spyc_iot/time.py
spyc_iot/wifi.py
spyc_iot-0.0.8.dist-info/LICENSE
spyc_iot-0.0.8.dist-info/METADATA
spyc_iot-0.0.8.dist-info/WHEEL
spyc_iot-0.0.8.dist-info/top_level.txt
spyc_iot-0.0.8.dist-info/RECORD
