Metadata-Version: 2.1
Name: spyc-iot
Version: 0.0.8
Summary: Package for common IOT usages. Developed by Shatin Pui Ying College.
Author: SPYC-IT
Author-email: ite@school.pyc.edu.hk
License: MIT
Classifier: Programming Language :: Python :: 3
Classifier: Operating System :: OS Independent
Requires-Python: >=3.6
License-File: LICENSE
